streamlit_subprocess/__init__.py
streamlit_subprocess-0.1.0.dist-info/LICENSE
streamlit_subprocess-0.1.0.dist-info/METADATA
streamlit_subprocess-0.1.0.dist-info/WHEEL
streamlit_subprocess-0.1.0.dist-info/RECORD
